{
  "db_name": "PostgreSQL",
  "query": "SELECT email, password_hash FROM users WHERE users.email = $1",
  "describe": {
    "columns": [
      {
        "ordinal": 0,
        "name": "email",
        "type_info": "Varchar"
      },
      {
        "ordinal": 1,
        "name": "password_hash",
        "type_info": "Varchar"
      }
    ],
    "parameters": {
      "Left": [
        "Text"
      ]
    },
    "nullable": [
      false,
      false
    ]
  },
  "hash": "d180d14bf40de8953dded58a9729fb91362180e39bc95d84a04e52d951240e98"
}
